MANIFEST.in
README.rst
setup.cfg
setup.py
accessstats/__init__.py
accessstats/client.py
accessstats/queries.py
accessstats/thrift/access_stats.thrift
scielo_accessstatsapi.egg-info/PKG-INFO
scielo_accessstatsapi.egg-info/SOURCES.txt
scielo_accessstatsapi.egg-info/dependency_links.txt
scielo_accessstatsapi.egg-info/requires.txt
scielo_accessstatsapi.egg-info/top_level.txt
tests/__init__.py
tests/test_accessstats.py
tests/test_queries.py
tests/custom_queries_templates/0000-0000.json
tests/custom_queries_templates/0000-0000_invalid.json